moveread/pipelines/auto_extraction/__init__.py
moveread/pipelines/auto_extraction/__init__.pyi
moveread/pipelines/auto_extraction/main.py
moveread/pipelines/auto_extraction/types.py
moveread_pipelines_auto_extract-0.1.11.dist-info/METADATA
moveread_pipelines_auto_extract-0.1.11.dist-info/WHEEL
moveread_pipelines_auto_extract-0.1.11.dist-info/top_level.txt
moveread_pipelines_auto_extract-0.1.11.dist-info/RECORD
