Metadata-Version: 2.1
Name: moveread-pipelines-auto-extract
Version: 0.1.11
Summary: Auto-extraction Moveread pipeline
Author-email: Marcel Claramunt <marcel@moveread.com>
Project-URL: repo, https://github.com/moveread/moveread-pipelines.git
Requires-Python: >=3.10
Requires-Dist: pure-cv
Requires-Dist: robust-extraction
Requires-Dist: moveread-annotations
Requires-Dist: pydantic ==2.*
Requires-Dist: haskellian
Requires-Dist: queue-api
Requires-Dist: lazy-loader
Requires-Dist: pipeteer
